autotranslate/__init__.py
autotranslate/lenuxtranslate.py
autotranslate/logger.py
lenuxtranslate-1.25.3.dist-info/LICENSE
lenuxtranslate-1.25.3.dist-info/METADATA
lenuxtranslate-1.25.3.dist-info/WHEEL
lenuxtranslate-1.25.3.dist-info/entry_points.txt
lenuxtranslate-1.25.3.dist-info/top_level.txt
lenuxtranslate-1.25.3.dist-info/RECORD
