Metadata-Version: 2.2
Name: lenuxtranslate
Version: 1.25.3
Summary: Argos Translate Tabanlı Türkçe Destekli Çeviri Kütüphanesi
Home-page: https://github.com/razzy-code/lenuxtranslatee
Author: razzy-code
Author-email: nsaylan0@gmail.com
Classifier: Programming Language :: Python :: 3
Classifier: License :: OSI Approved :: MIT License
Classifier: Operating System :: OS Independent
Requires-Python: >=3.7
License-File: LICENSE
Requires-Dist: argostranslate
Requires-Dist: colorama
Dynamic: author
Dynamic: author-email
Dynamic: classifier
Dynamic: description
Dynamic: description-content-type
Dynamic: home-page
Dynamic: requires-dist
Dynamic: requires-python
Dynamic: summary
